LICENSE.txt
MANIFEST.in
README.rst
setup.cfg
setup.py
MultiSim.egg-info/PKG-INFO
MultiSim.egg-info/SOURCES.txt
MultiSim.egg-info/dependency_links.txt
MultiSim.egg-info/requires.txt
MultiSim.egg-info/top_level.txt
multisim/__init__.py
multisim/all_parts.py
multisim/controls.py
multisim/data_class.py
multisim/flownet.py
multisim/precomp_funs.py
multisim/simenv.py
multisim/std_parts.py
multisim/utility_functions.py
multisim/version.py
multisim/data_tables/heat_exchangers.pkl
multisim/data_tables/heat_exchangers.xlsx
multisim/data_tables/material_props.pkl
multisim/data_tables/material_props.xlsx
multisim/data_tables/material_props_dry_air.pkl
multisim/data_tables/material_props_dry_air.xlsx
multisim/data_tables/material_props_water.pkl
multisim/data_tables/material_props_water.xlsx
multisim/data_tables/phelix-quarterly-data-data-data.xls
multisim/data_tables/pipe_specs.pkl
multisim/data_tables/pipe_specs.xlsx
multisim/parts/__init__.py
multisim/parts/chp_plant.py
multisim/parts/connector_3w.py
multisim/parts/controllers.py
multisim/parts/heated_pipe.py
multisim/parts/heatexchanger.py
multisim/parts/hex_condensing_polynome.py
multisim/parts/hex_num.py
multisim/parts/mixingvalve.py
multisim/parts/pipe.py
multisim/parts/pipe2D.py
multisim/parts/pipe_branched.py
multisim/parts/pipe_nonopt.py
multisim/parts/pipe_with_pump.py
multisim/parts/pipe_with_valve.py
multisim/parts/pump.py
multisim/parts/tes.py
multisim/parts/tes_nonopt.py
multisim/parts/part_modules/__init__.py
multisim/parts/part_modules/chp_with_fluegas_hex.py
multisim/parts/part_modules/consumers.py
multisim/parts/part_modules/suppliers.py