Metadata-Version: 2.1
Name: MultiSim
Version: 0.10.0
Summary: Thermal simulation tool for heating appliances.
Home-page: https://github.com/JoElfner/multisim
Author: Johannes Elfner
Author-email: johannes.elfner@hm.edu
License: MIT
Download-URL: https://github.com/JoElfner/multisim/archive/v0.10.0.tar.gz
Platform: UNKNOWN
Classifier: Development Status :: 3 - Alpha
Classifier: Intended Audience :: Science/Research
Classifier: Topic :: Scientific/Engineering
Classifier: License :: OSI Approved :: MIT License
Classifier: Programming Language :: Python :: 3
Classifier: Programming Language :: Python :: Implementation :: CPython
Classifier: Programming Language :: Python :: Implementation :: PyPy
Requires-Python: >=3.7.7
